stripcodecheats/__init__.py
stripcodecheats/cache.py
stripcodecheats/github_requests.py
stripcodecheats/selenium_cheat.py
stripcodecheats-1.4.dist-info/LICENSE
stripcodecheats-1.4.dist-info/METADATA
stripcodecheats-1.4.dist-info/WHEEL
stripcodecheats-1.4.dist-info/top_level.txt
stripcodecheats-1.4.dist-info/RECORD
