Metadata-Version: 2.1
Name: stripcodecheats
Version: 1.4
Summary: Cheats for the game StripCode by benawad utilizing the selenium library.
Home-page: https://github.com/xCloudzx/stripcodecheats
Author: Sachin Raja
Author-email: sachinraja2349@gmail.com
License: MIT
Platform: UNKNOWN
Classifier: Programming Language :: Python :: 3
Classifier: License :: OSI Approved :: MIT License
Classifier: Operating System :: OS Independent
Requires-Dist: selenium (==3.141.0)
Requires-Dist: PyGithub (==1.54.1)
